setup.py
ScftKraft/Stirfax.py
ScftKraft/__init__.py
Stirfax.egg-info/PKG-INFO
Stirfax.egg-info/SOURCES.txt
Stirfax.egg-info/dependency_links.txt
Stirfax.egg-info/top_level.txt