Metadata-Version: 2.1
Name: Stirfax
Version: 8.0.5
Summary: By @A_T_9 In telegram 
Author: Programmer RESS 
Classifier: Programming Language :: Python :: 3
Classifier: Operating System :: OS Independent
Classifier: License :: OSI Approved :: MIT License
